academic_tracker/__init__.py
academic_tracker/__main__.py
academic_tracker/_version.py
academic_tracker/athr_srch_emails_and_reports.py
academic_tracker/athr_srch_modularized.py
academic_tracker/athr_srch_webio.py
academic_tracker/citation_parsing.py
academic_tracker/emails_and_reports_helpers.py
academic_tracker/fileio.py
academic_tracker/helper_functions.py
academic_tracker/ref_srch_emails_and_reports.py
academic_tracker/ref_srch_modularized.py
academic_tracker/ref_srch_webio.py
academic_tracker/tracker_schema.py
academic_tracker/user_input_checking.py
academic_tracker/webio.py
academic_tracker-2.0.1.dist-info/LICENSE
academic_tracker-2.0.1.dist-info/METADATA
academic_tracker-2.0.1.dist-info/WHEEL
academic_tracker-2.0.1.dist-info/entry_points.txt
academic_tracker-2.0.1.dist-info/top_level.txt
academic_tracker-2.0.1.dist-info/RECORD
