Metadata-Version: 2.1
Name: academic_tracker
Version: 2.0.1
Summary: Find publications on PubMed, Crossref, ORCID, and Google Scholar for given authors or references.
License: The Clear BSD License with Extra Clause
Project-URL: Homepage, https://github.com/MoseleyBioinformaticsLab/academic_tracker
Project-URL: Documentation, https://moseleybioinformaticslab.github.io/academic_tracker/
Project-URL: GitHub, https://github.com/MoseleyBioinformaticsLab/academic_tracker
Project-URL: Issues, https://github.com/MoseleyBioinformaticsLab/academic_tracker/issues
Keywords: PubMed,publications,citations,Crossref,ORCID,Google Scholar
Classifier: Environment :: Console
Classifier: Intended Audience :: Developers
Classifier: Intended Audience :: Science/Research
Classifier: License :: OSI Approved :: BSD License
Classifier: Operating System :: OS Independent
Classifier: Programming Language :: Python :: 3.8
Classifier: Programming Language :: Python :: 3.9
Classifier: Programming Language :: Python :: 3.10
Classifier: Programming Language :: Python :: 3.11
Classifier: Programming Language :: Python :: 3.12
Classifier: Topic :: Software Development :: Libraries :: Python Modules
Requires-Python: >=3.8
License-File: LICENSE
Requires-Dist: docopt>=0.6.2
Requires-Dist: pymed>=0.8.9
Requires-Dist: jsonschema>=4.4.0
Requires-Dist: habanero>=1.0.0
Requires-Dist: orcid>=1.0.3
Requires-Dist: scholarly>=1.4.5
Requires-Dist: beautifulsoup4>=4.9.3
Requires-Dist: fuzzywuzzy>=0.18.0
Requires-Dist: python-docx>=0.8.11
Requires-Dist: pandas>=1.3.5
Requires-Dist: openpyxl>=2.6.2
Requires-Dist: requests>=2.21.0
Requires-Dist: deepdiff>=5.7.0
Requires-Dist: setuptools-scm>=7.0.5
